odoo/addons/stock_scrap_tier_validation/README.rst
odoo/addons/stock_scrap_tier_validation/__init__.py
odoo/addons/stock_scrap_tier_validation/__manifest__.py
odoo/addons/stock_scrap_tier_validation/data/mail_message_subtype_data.xml
odoo/addons/stock_scrap_tier_validation/i18n/es.po
odoo/addons/stock_scrap_tier_validation/i18n/it.po
odoo/addons/stock_scrap_tier_validation/i18n/stock_scrap_tier_validation.pot
odoo/addons/stock_scrap_tier_validation/models/__init__.py
odoo/addons/stock_scrap_tier_validation/models/stock_picking.py
odoo/addons/stock_scrap_tier_validation/models/stock_scrap.py
odoo/addons/stock_scrap_tier_validation/models/tier_definition.py
odoo/addons/stock_scrap_tier_validation/readme/CONFIGURE.md
odoo/addons/stock_scrap_tier_validation/readme/CONTRIBUTORS.md
odoo/addons/stock_scrap_tier_validation/readme/DESCRIPTION.md
odoo/addons/stock_scrap_tier_validation/readme/INSTALL.md
odoo/addons/stock_scrap_tier_validation/readme/USAGE.md
odoo/addons/stock_scrap_tier_validation/static/description/icon.png
odoo/addons/stock_scrap_tier_validation/static/description/index.html
odoo/addons/stock_scrap_tier_validation/tests/__init__.py
odoo/addons/stock_scrap_tier_validation/tests/test_tier_validation.py
odoo/addons/stock_scrap_tier_validation/views/stock_scrap_view.xml
odoo_addon_stock_scrap_tier_validation-17.0.1.0.0.3.dist-info/METADATA
odoo_addon_stock_scrap_tier_validation-17.0.1.0.0.3.dist-info/WHEEL
odoo_addon_stock_scrap_tier_validation-17.0.1.0.0.3.dist-info/top_level.txt
odoo_addon_stock_scrap_tier_validation-17.0.1.0.0.3.dist-info/RECORD
