Metadata-Version: 2.1
Name: odoo-addon-stock_scrap_tier_validation
Version: 17.0.1.0.0.3
Requires-Python: >=3.10
Requires-Dist: odoo-addon-base_tier_validation>=17.0dev,<17.1dev
Requires-Dist: odoo>=17.0a,<17.1dev
Summary: Stock Scrap Tier Validation
Home-page: https://github.com/OCA/stock-logistics-workflow
License: AGPL-3
Author: Jarsa, Odoo Community Association (OCA)
Author-email: support@odoo-community.org
Classifier: Programming Language :: Python
Classifier: Framework :: Odoo
Classifier: Framework :: Odoo :: 17.0
Classifier: License :: OSI Approved :: GNU Affero General Public License v3
